README.md
setup.py
gladia_api_utils/CoquiEngineHelper.py
gladia_api_utils/OVHFileManager.py
gladia_api_utils/TorchvisionModelHelper.py
gladia_api_utils/__init__.py
gladia_api_utils/add_routes_to_router.py
gladia_api_utils/apis_for_subprocess.py
gladia_api_utils/casting.py
gladia_api_utils/citation.py
gladia_api_utils/fastapi_runner.py
gladia_api_utils/file_management.py
gladia_api_utils/get_activated_task_path.py
gladia_api_utils/image_management.py
gladia_api_utils/io.py
gladia_api_utils/model_management.py
gladia_api_utils/nlp.py
gladia_api_utils/options.py
gladia_api_utils/prepare_in_custom_env.py
gladia_api_utils/responses.py
gladia_api_utils/run_process.py
gladia_api_utils/secret_management.py
gladia_api_utils/submodules.py
gladia_api_utils/system.py
gladia_api_utils/task_management.py
gladia_api_utils.egg-info/PKG-INFO
gladia_api_utils.egg-info/SOURCES.txt
gladia_api_utils.egg-info/dependency_links.txt
gladia_api_utils.egg-info/not-zip-safe
gladia_api_utils.egg-info/requires.txt
gladia_api_utils.egg-info/top_level.txt
gladia_api_utils/deepspeed_helper/__init__.py
gladia_api_utils/deepspeed_helper/prepare.py
gladia_api_utils/inpainting_helper/helper.py
gladia_api_utils/inpainting_helper/model_manager.py
gladia_api_utils/inpainting_helper/predictor.py
gladia_api_utils/inpainting_helper/schema.py
gladia_api_utils/model_architectures/Maxim.py
gladia_api_utils/model_architectures/__init__.py
gladia_api_utils/tester/__init__.py
gladia_api_utils/tester/__main__.py
gladia_api_utils/tester/constants.py
gladia_api_utils/tester/default_tests.py
gladia_api_utils/tester/test_autogenerated.py
gladia_api_utils/tester/utils/__init__.py
gladia_api_utils/tester/utils/get_data_to_test.py
gladia_api_utils/triton_helper/TritonClient.py
gladia_api_utils/triton_helper/__init__.py
gladia_api_utils/triton_helper/data_processing.py
gladia_api_utils/triton_helper/download_active_models.py
gladia_api_utils/triton_helper/helper.py