Metadata-Version: 2.1
Name: gladia-api-utils
Version: 0.1.20
Summary: Utils for Gladia APIs Framework
Home-page: UNKNOWN
Author: Jean-Louis Queguiner
Author-email: jlqueguiner@gladia.io
License: MIT
Keywords: ai api fastapi artificial_intelligence gladia
Platform: UNKNOWN
Classifier: Development Status :: 1 - Planning
Classifier: License :: OSI Approved :: MIT License
Classifier: Programming Language :: Python :: 3
Classifier: Operating System :: OS Independent
